{"client":"Thunder Client","collectionName":"SW202203","dateExported":"2022-11-02T01:04:30.149Z","version":"1.1","folders":[{"_id":"c6a18138-8658-4fbb-8786-35b7ae57d210","name":"CashFlow","containerId":"","created":"2022-09-29T23:51:59.258Z","sortNum":10000,"settings":{"headers":[],"auth":{"type":"bearer","bearer":"eyJhbGciOiJIUzI1NiIsInR5cCI6IkpXVCJ9.eyJuYW1lIjoiT3JsYW5kbyBCZXRhbmNvdXJ0aCIsImVtYWlsIjoib2JldGFuY291cnRodW5pY2FoQGdtYWlsLmNvbSIsImF2YXRhciI6IiIsIl9pZCI6IjYzNTlkNzcwZmVjYjg5ZDJjNmQxZDNmNSIsImlhdCI6MTY2NzM0ODU4OH0.DubkaMP35_ukO5IOA3MECp313Mj9aTUSCdQl8IKFdv0"},"tests":[]}},{"_id":"c2a79823-ed34-4443-b991-757a311a2f1c","name":"Users","containerId":"","created":"2022-10-24T23:23:20.746Z","sortNum":20000}],"requests":[{"_id":"6a54b84c-c5ad-48d7-84e7-59b1c17c130f","colId":"9bf92984-5fc3-4213-a493-af88e02e5a74","containerId":"c6a18138-8658-4fbb-8786-35b7ae57d210","name":"get All","url":"{{HOST}}/cashflow/","method":"GET","sortNum":30000,"created":"2022-09-29T23:52:11.186Z","modified":"2022-11-02T00:46:37.029Z","headers":[],"params":[],"tests":[]},{"_id":"a3390df5-c35d-46cb-974f-f24144996122","colId":"9bf92984-5fc3-4213-a493-af88e02e5a74","containerId":"c6a18138-8658-4fbb-8786-35b7ae57d210","name":"get Count","url":"{{HOST}}/cashflow/count","method":"GET","sortNum":35000,"created":"2022-10-13T00:37:03.986Z","modified":"2022-10-13T00:37:38.972Z","headers":[],"params":[],"tests":[]},{"_id":"b97b96ee-3f9b-4a1f-99c4-c08177ee4c69","colId":"9bf92984-5fc3-4213-a493-af88e02e5a74","containerId":"c6a18138-8658-4fbb-8786-35b7ae57d210","name":"find By  Id","url":"{{HOST}}/cashflow/byindex/{id}","method":"GET","sortNum":40000,"created":"2022-09-30T00:27:40.508Z","modified":"2022-10-12T06:39:18.546Z","headers":[],"params":[{"name":"id","value":"63465ec4740f94fb939fb67b","isPath":true}],"tests":[]},{"_id":"114f3cb4-35d6-49d1-948d-2b9e4c1086da","colId":"9bf92984-5fc3-4213-a493-af88e02e5a74","containerId":"c6a18138-8658-4fbb-8786-35b7ae57d210","name":"New","url":"{{HOST}}/cashflow/new","method":"POST","sortNum":50000,"created":"2022-09-30T00:32:57.132Z","modified":"2022-11-02T00:45:44.731Z","headers":[],"params":[],"body":{"type":"formencoded","raw":"","form":[{"name":"type","value":"INCOME"},{"name":"date","value":"2022-11-01T23:56:27.320Z"},{"name":"amount","value":"1550"},{"name":"description","value":"Tutoria de React"}]},"tests":[]},{"_id":"1de60952-17c3-4952-ad1c-9e8f4039ce66","colId":"9bf92984-5fc3-4213-a493-af88e02e5a74","containerId":"c6a18138-8658-4fbb-8786-35b7ae57d210","name":"Delete","url":"{{HOST}}/cashflow/delete/{id}","method":"DELETE","sortNum":60000,"created":"2022-09-30T00:50:25.245Z","modified":"2022-10-21T00:26:45.682Z","headers":[],"params":[{"name":"id","value":"6347582f355195e0c22659f1","isPath":true}],"tests":[]},{"_id":"34047292-826d-4a30-b08b-ebc1dca3e59b","colId":"9bf92984-5fc3-4213-a493-af88e02e5a74","containerId":"c6a18138-8658-4fbb-8786-35b7ae57d210","name":"Update","url":"{{HOST}}/cashflow/update/{id}","method":"PUT","sortNum":70000,"created":"2022-09-30T01:21:21.325Z","modified":"2022-10-12T06:37:28.377Z","headers":[],"params":[{"name":"id","value":"6346607a355195e0c22659ee","isPath":true}],"body":{"type":"formencoded","raw":"","form":[{"name":"type","value":"INCOME"},{"name":"date","value":"2022-09-29T23:55:27.320Z"},{"name":"amount","value":"250"},{"name":"description","value":"Otro Ingreso Actualizado"}]},"tests":[]},{"_id":"ef7bd130-0d57-418c-82da-ac5a291934fa","colId":"9bf92984-5fc3-4213-a493-af88e02e5a74","containerId":"c6a18138-8658-4fbb-8786-35b7ae57d210","name":"ValidatorTest","url":"{{HOST}}/cashflow/testvalidator","method":"POST","sortNum":70000,"created":"2022-09-30T23:56:51.379Z","modified":"2022-10-01T00:00:34.816Z","headers":[],"params":[],"body":{"type":"formencoded","raw":"","form":[{"name":"email","value":"error@unicah.edu"}]},"tests":[]},{"_id":"21733666-0c3a-426c-8333-1afe0ed14bd2","colId":"9bf92984-5fc3-4213-a493-af88e02e5a74","containerId":"c2a79823-ed34-4443-b991-757a311a2f1c","name":"Sign In","url":"{{HOST}}/security/signin","method":"POST","sortNum":80000,"created":"2022-10-24T23:23:39.092Z","modified":"2022-10-27T00:57:20.807Z","headers":[{"name":"apikey","value":"cuandoLosGatosNoEstan"}],"params":[],"body":{"type":"formencoded","raw":"","form":[{"name":"name","value":"Orlando Betancourth"},{"name":"email","value":"obetancourthunicah@gmail.com"},{"name":"password","value":"Konoha%33"}]},"tests":[]},{"_id":"c49094a0-d0ea-4f34-9ecf-3ca9a3c1301b","colId":"9bf92984-5fc3-4213-a493-af88e02e5a74","containerId":"c2a79823-ed34-4443-b991-757a311a2f1c","name":"Login","url":"{{HOST}}/security/login","method":"POST","sortNum":90000,"created":"2022-10-28T00:36:09.556Z","modified":"2022-11-01T00:53:45.664Z","headers":[{"name":"apikey","value":"cuandoLosGatosNoEstan"}],"params":[],"body":{"type":"formencoded","raw":"","form":[{"name":"email","value":"obetancourthunicah@gmail.com"},{"name":"password","value":"Konoha%33"},{"name":"2","value":""}]},"tests":[]},{"_id":"43d78322-981b-46f9-a6fa-4192095f587f","colId":"9bf92984-5fc3-4213-a493-af88e02e5a74","containerId":"c2a79823-ed34-4443-b991-757a311a2f1c","name":"add Role","url":"{{HOST}}/security/addrole/{id}","method":"POST","sortNum":100000,"created":"2022-11-01T00:54:29.165Z","modified":"2022-11-01T00:58:15.009Z","headers":[{"name":"apikey","value":"cuandoLosGatosNoEstan"}],"params":[{"name":"id","value":"6359d770fecb89d2c6d1d3f5","isPath":true}],"body":{"type":"formencoded","raw":"","form":[{"name":"role","value":"admin"}]},"tests":[]}],"settings":{"headers":[{"name":"apikey","value":"cuandoLosGatosNoEstan"}],"tests":[]}}
